odoo/addons/fieldservice_fleet/README.rst
odoo/addons/fieldservice_fleet/__init__.py
odoo/addons/fieldservice_fleet/__manifest__.py
odoo/addons/fieldservice_fleet/hooks.py
odoo/addons/fieldservice_fleet/i18n/es.po
odoo/addons/fieldservice_fleet/i18n/es_AR.po
odoo/addons/fieldservice_fleet/i18n/es_CL.po
odoo/addons/fieldservice_fleet/i18n/fieldservice_fleet.pot
odoo/addons/fieldservice_fleet/i18n/it.po
odoo/addons/fieldservice_fleet/i18n/pt_BR.po
odoo/addons/fieldservice_fleet/i18n/tr.po
odoo/addons/fieldservice_fleet/models/__init__.py
odoo/addons/fieldservice_fleet/models/fleet_vehicle.py
odoo/addons/fieldservice_fleet/models/fsm_vehicle.py
odoo/addons/fieldservice_fleet/readme/CONFIGURE.rst
odoo/addons/fieldservice_fleet/readme/CONTRIBUTORS.rst
odoo/addons/fieldservice_fleet/readme/CREDITS.rst
odoo/addons/fieldservice_fleet/readme/DESCRIPTION.rst
odoo/addons/fieldservice_fleet/readme/INSTALL.rst
odoo/addons/fieldservice_fleet/readme/ROADMAP.rst
odoo/addons/fieldservice_fleet/readme/USAGE.rst
odoo/addons/fieldservice_fleet/static/description/icon.png
odoo/addons/fieldservice_fleet/static/description/index.html
odoo/addons/fieldservice_fleet/tests/__init__.py
odoo/addons/fieldservice_fleet/tests/test_fsm_fleet_wizard.py
odoo/addons/fieldservice_fleet/views/fleet_vehicle.xml
odoo/addons/fieldservice_fleet/views/fsm_vehicle.xml
odoo/addons/fieldservice_fleet/wizard/__init__.py
odoo/addons/fieldservice_fleet/wizard/fsm_fleet_wizard.py
odoo/addons/fieldservice_fleet/wizard/fsm_fleet_wizard.xml
odoo13_addon_fieldservice_fleet-13.0.1.0.1.dev11.dist-info/METADATA
odoo13_addon_fieldservice_fleet-13.0.1.0.1.dev11.dist-info/WHEEL
odoo13_addon_fieldservice_fleet-13.0.1.0.1.dev11.dist-info/top_level.txt
odoo13_addon_fieldservice_fleet-13.0.1.0.1.dev11.dist-info/RECORD
